{
    "Fiscal year": {
        "type": "text"
    },
    "Section name": {
        "type": "text"
    },
    "IRTC percent": {
        "type": "real"
    },
    "Knowledge for development (marker)": {
        "type": "int"
    },
    "Participatory development and good governance": {
        "type": "int"
    },
    "Section ID": {
        "type": "text"
    },
    "Trade development (marker)": {
        "type": "int"
    },
    "PBA type": {
        "type": "text"
    },
    "Desertification (marker)": {
        "type": "int"
    },
    "Sector name": {
        "type": "text"
    },
    "Gender equality (marker)": {
        "type": "int"
    },
    "Status": {
        "type": "text"
    },
    "Sector percent": {
        "type": "real"
    },
    "Organisation type": {
        "type": "text"
    },
    "Organisation class": {
        "type": "text"
    },
    "Project number": {
        "type": "text"
    },
    "Maximum CIDA contribution (project-level)": {
        "type": "real"
    },
    "Branch ID": {
        "type": "text"
    },
    "Branch name": {
        "type": "text"
    },
    "Division ID": {
        "type": "text"
    },
    "Division name": {
        "type": "text"
    },
    "Regional program (marker)": {
        "type": "int"
    },
    "Fund centre ID": {
        "type": "int"
    },
    "Fund centre name": {
        "type": "text"
    },
    "Untied amount(Project-level budget)": {
        "type": "real"
    },
    "FSTC percent": {
        "type": "real"
    },
    "CFLI (marker)": {
        "type": "int"
    },
    "CIDA business delivery model (old)": {
        "type": "text"
    },
    "Programming process (new)": {
        "type": "text"
    },
    "Bilateral aid (international marker)": {
        "type": "int"
    },
    "Enviromental sustainability (marker)": {
        "type": "int"
    },
    "Climate change adaptation (marker)": {
        "type": "int"
    },
    "Climate change mitigation (marker)": {
        "type": "int"
    }
}